README.md
setup.py
src/api/__init__.py
src/api/apitable_databus_client.py
src/zzq_strings_sum.egg-info/PKG-INFO
src/zzq_strings_sum.egg-info/SOURCES.txt
src/zzq_strings_sum.egg-info/dependency_links.txt
src/zzq_strings_sum.egg-info/requires.txt
src/zzq_strings_sum.egg-info/top_level.txt