Metadata-Version: 2.1
Name: zzq-strings-sum
Version: 0.6.0
Summary: A client for Databus API
Home-page: UNKNOWN
Author: zzq
Author-email: zhaozhiqiang@vikadata.com
License: UNKNOWN
Platform: UNKNOWN
